Workbook

Sheet Sheet1
B10: Property Address:
D11: Take Down Fiancing | F11: Stabilized Financing | I11: Operating Expenses (Annual)
B12: Total Acquisition Price | C12: 215000 | D12: Construction Loan Down Payment | E12: 0.2 | F12: Refinance Loan LTARV | G12: 0.75 | I12: Real Estate Taxes | J12: 3000
B13: Est. Rehab Budget | C13: 80000 | D13: Construction Loan Origination Points | E13: 0.02 | F13: Refinance Loan Origination Points | G13: 0.01 | I13: Insurance | J13: 1200
B14: Est. After Repair Value | C14: 399950 | D14: Construction Interest Rate | E14: 0.12 | F14: Refinance Loan Interest Rate | G14: 0.075 | I14: Repairs & Maintenance | J14: 1650
B15: Holding Period (Months) | C15: 4 | F15: Refinance Method | G15: LTV | I15: Utilities | J15: 0
F16: Min DSCR (if DSCR loan) | G16: 1.2 | I16: Property Mgmt (%) | J16: 0.08
B17: Loan Down Payment | I17: Vacancy Rate (%) | J17: 0.05
B19: Purchase Price | D19: =C12 -> 215000
B20: Est. Rehab Costs | D20: =C13 -> 80000
B21: Total Costs for Financing | D21: =D19+D20 -> 295000
B22: Down Payment | C22: =E12 -> 0.2 | D22: =D21*E12 -> 59000
B24: Construction Promissory Note Amount
B26: Loan Basis | D26: =D21-D22 -> 236000
B27: Loan Points | C27: =E13 -> 0.02 | D27: =D26*E13 -> 4720
B28: Loan Fees | D28: 800
B29: Promissory Note Amount | D29: =SUM(D26:D28) -> 241520
B31: Pre-Refinance Financing Direct Costs (during construction)
B33: Purchase Price
B34: Est. Rehab Costs | D34: =D20 -> 80000
B35: Acquistion Closing Costs | D35: 1500
B36: Interest Payments (Monthly) | C36: =D36/C15 -> 2415.2 | D36: =(D29)*(E14)/12*(C15) -> 9660.8
B37: Real Estate Taxes (Monthly) | C37: =J12/12 -> 250 | D37: =C37*C15 -> 1000
B38: Insurance (Monthly) | C38: =J13/12 -> 100 | D38: =C38*C15 -> 400
B39: Utilities (Monthly) | C39: 200 | D39: =C39*C15 -> 800
B40: Total Direct Costs | D40: =D19+D20+D27+D28+D35+D36+D37+D38+D39 -> 313880.8
B41: Total Cash Invested | D41: =D22+D35+SUM(D36:D39) -> 72360.8
B43: Refinance Promissory Note Amount
B44: DSCR-Supported Max Loan (Note) | D44: =IFERROR(-PV(G14/12,360,(D65/G16)/12),0) -> 227040.48
B45: Loan Basis | D45: =IF(G15="DSCR",(D44-D47)/(1+G13),C14*G12) -> 299962.5
B46: Loan Points | C46: =G13 -> 0.01 | D46: =C46*D45 -> 2999.625
B47: Loan Fees | D47: 800
B48: Promissory Note Amount | D48: =SUM(D45:D47) -> 303762.12
B49: Construction Loan Promissory Note | D49: =-D29 -> -241520
B50: Cash (In)/Out From Refinance | D50: =D48+D49-D46-D47 -> 58442.5
B51: Total Cash Remaining in Project | D51: =D41-D50 -> 13918.3
B53: Cash Flows
C54: Monthly | D54: Annual
B55: Gross Rental Income | C55: 2750 | D55: =C55*12 -> 33000
B56: Vacancy Loss | C56: =ROUND(D56/12,0) -> 138 | D56: =ROUND(D55*J17,0) -> 1650
B57: Effective Gross Income | C57: =C55-C56 -> 2612 | D57: =D55-D56 -> 31350
B58: Operating Expenses:
B59: Real Estate Taxes | C59: =ROUND(D59/12,0) -> 250 | D59: =J12 -> 3000
B60: Insurance | C60: =ROUND(D60/12,0) -> 100 | D60: =J13 -> 1200
B61: Utilities | C61: =ROUND(D61/12,0) -> 0 | D61: =J15 -> 0
B62: Property Management | C62: =ROUND(C55*J16,0) -> 220 | D62: =C62*12 -> 2640
B63: Repairs & Maintenance | C63: =ROUND(D63/12,0) -> 138 | D63: =J14 -> 1650
B64: Total Operating Expenses | C64: =SUM(C59:C63) -> 708 | D64: =SUM(D59:D63) -> 8490
B65: Net Operating Income (NOI) | C65: =C57-C64 -> 1904 | D65: =D57-D64 -> 22860
B66: Debt Service | C66: =-ROUND(PMT(G14/12,360,D48),0) -> 2124 | D66: =C66*12 -> 25488
B67: Cash Flow | C67: =C65-C66 -> -220 | D67: =D65-D66 -> -2628
B69: DEAL SUMMARY
B70: Cash Left in Deal | D70: =D51 -> 13918.3
B71: Monthly Cash Flow | D71: =C67 -> -220
B72: Cash-on-Cash Return | D72: =IFERROR(D67/D51,"n/a") -> -0.18881616
B73: Return on Equity (Yr 1) | D73: =IFERROR(D67/(C14-D48),"n/a") -> -0.027321531
B74: 5-Year IRR | D74: =IFERROR('5-Year Projection'!C21,"n/a") -> 0.53661366
B75: Equity Captured (ARV - Loan Balance) | D75: =C14-D48 -> 96187.875
B76: DSCR at Refinance | D76: =IFERROR(D65/D66,"n/a") -> 0.89689266
B77: Max Allowable Offer (75% Rule) | D77: =C14*0.75-C13 -> 219962.5
B80: DISCLAIMER AND WAIVER OF CLAIMS. The foregoing Proforma is based on estimates only and does not constitute a commitment, representation, warranty, or agreement binding on PROJECT RE, LLC, or any of its affiliated companies, members, managers, brokers, agents, or employees, and PROJECT RE or any of its affiliated companies hereby disclaims any such warranty, representation, commitment or agreement. PROJECT RE or any of its affiliated companies further disclaims any warranty or representation of any kind or nature regarding the condition or attributes of the property which is the subject of the Proforma (the “Property”), including without limitation the Property’s structural integrity, potential for improvement, or existing or potential hazardous materials contamination. Client acknowledges that the purchase and renovation of the Property is a speculative investment which involves a substantial degree of risk of loss of his/her/its entire investment; Client understands and takes full cognizance of, and responsibility for, the risk factors related to the purchase of the Property, and acknowledges his/her/its responsibility to conduct investigation and due diligence, independent of the Proforma or other information provided by PROJECT RE or any of its affiliated companies. Client waives and releases PROJECT RE or any of its affiliated companies from any claim or liability arising from any loss sustained by Client on account of his/her/its reliance on the Proforma or other information provided by PROJECT RE or any of its affiliated companies regarding the acquisition and development of the Property. NO GUARANTEE OF ACCURACY. Neither James Dainard nor PROJECT RE or any of its affiliated companies guarantees, warrants, or represents the accuracy, completeness, or reliability of this calculator or any of its outputs. All projections, estimated profit, costs, returns, and formulas contained herein are provided for illustrative purposes only, may contain errors, and rely on assumptions that may not occur. The Client/Investor is solely responsible for independently verifying all projections, estimated profit, costs, and formulas, and for confirming their accuracy with his/her/its own advisors, prior to relying on them for any investment decision. PROPRIETARY AND CONFIDENTIAL INFORMATION. This calculator, together with its formulas, structure, methodology, and content, constitutes the proprietary and confidential information of James Dainard and PROJECT RE or any of its affiliated companies. By accessing or using this calculator, the user acknowledges its proprietary nature and agrees not to copy, reproduce, distribute, disclose, or otherwise share it, in whole or in part, with any other person or entity without the prior written consent of PROJECT RE or any of its affiliated companies.

Sheet 5-Year Projection
B2: Multi-Year Projection Assumptions
B3: Annual Appreciation Rate | C3: 0.03
B4: Annual Rent Growth | C4: 0.02
B5: Annual Expense Growth | C5: 0.02
B6: Selling Costs (% of Sale Price) | C6: 0.06
B8: Year | C8: Year 0 | D8: Year 1 | E8: Year 2 | F8: Year 3 | G8: Year 4 | H8: Year 5
B9: Property Value | C9: =Sheet1!$C$14*(1+$C$3)^0 -> 399950 | D9: =Sheet1!$C$14*(1+$C$3)^1 -> 411948.5 | E9: =Sheet1!$C$14*(1+$C$3)^2 -> 424306.96 | F9: =Sheet1!$C$14*(1+$C$3)^3 -> 437036.16 | G9: =Sheet1!$C$14*(1+$C$3)^4 -> 450147.25 | H9: =Sheet1!$C$14*(1+$C$3)^5 -> 463651.67
B10: Gross Rent | C10: 0 | D10: =Sheet1!$D$55*(1+$C$4)^0 -> 33000 | E10: =Sheet1!$D$55*(1+$C$4)^1 -> 33660 | F10: =Sheet1!$D$55*(1+$C$4)^2 -> 34333.2 | G10: =Sheet1!$D$55*(1+$C$4)^3 -> 35019.864 | H10: =Sheet1!$D$55*(1+$C$4)^4 -> 35720.261
B11: Effective Gross Income | C11: 0 | D11: =D10*(1-Sheet1!$J$17) -> 31350 | E11: =E10*(1-Sheet1!$J$17) -> 31977 | F11: =F10*(1-Sheet1!$J$17) -> 32616.54 | G11: =G10*(1-Sheet1!$J$17) -> 33268.871 | H11: =H10*(1-Sheet1!$J$17) -> 33934.248
B12: Operating Expenses | C12: 0 | D12: =Sheet1!$D$64*(1+$C$5)^0 -> 8490 | E12: =Sheet1!$D$64*(1+$C$5)^1 -> 8659.8 | F12: =Sheet1!$D$64*(1+$C$5)^2 -> 8832.996 | G12: =Sheet1!$D$64*(1+$C$5)^3 -> 9009.6559 | H12: =Sheet1!$D$64*(1+$C$5)^4 -> 9189.849
B13: NOI | C13: 0 | D13: =D11-D12 -> 22860 | E13: =E11-E12 -> 23317.2 | F13: =F11-F12 -> 23783.544 | G13: =G11-G12 -> 24259.215 | H13: =H11-H12 -> 24744.399
B14: Debt Service | C14: 0 | D14: =Sheet1!$D$66 -> 25488 | E14: =Sheet1!$D$66 -> 25488 | F14: =Sheet1!$D$66 -> 25488 | G14: =Sheet1!$D$66 -> 25488 | H14: =Sheet1!$D$66 -> 25488
B15: Cash Flow | C15: 0 | D15: =D13-D14 -> -2628 | E15: =E13-E14 -> -2170.8 | F15: =F13-F14 -> -1704.456 | G15: =G13-G14 -> -1228.7851 | H15: =H13-H14 -> -743.60082
B16: Loan Balance (EOY) | C16: =Sheet1!$D$48 -> 303762.12 | D16: =PV(Sheet1!$G$14/12,360-12*1,PMT(Sheet1!$G$14/12,360,Sheet1!$D$48)) -> 300961.94 | E16: =PV(Sheet1!$G$14/12,360-12*2,PMT(Sheet1!$G$14/12,360,Sheet1!$D$48)) -> 297944.37 | F16: =PV(Sheet1!$G$14/12,360-12*3,PMT(Sheet1!$G$14/12,360,Sheet1!$D$48)) -> 294692.54 | G16: =PV(Sheet1!$G$14/12,360-12*4,PMT(Sheet1!$G$14/12,360,Sheet1!$D$48)) -> 291188.26 | H16: =PV(Sheet1!$G$14/12,360-12*5,PMT(Sheet1!$G$14/12,360,Sheet1!$D$48)) -> 287411.94
B17: Equity | C17: =C9-C16 -> 96187.875 | D17: =D9-D16 -> 110986.56 | E17: =E9-E16 -> 126362.58 | F17: =F9-F16 -> 142343.62 | G17: =G9-G16 -> 158958.99 | H17: =H9-H16 -> 176239.73
B18: Net Sale Proceeds (Y5) | C18: 0 | D18: 0 | E18: 0 | F18: 0 | G18: 0 | H18: =H9*(1-$C$6)-H16 -> 148420.63
B19: Net Cash Flow to Investor | C19: =-Sheet1!$D$51 -> -13918.3 | D19: =D15 -> -2628 | E19: =E15 -> -2170.8 | F19: =F15 -> -1704.456 | G19: =G15 -> -1228.7851 | H19: =H15+H18 -> 147677.03
B21: Projected 5-Year IRR | C21: =IFERROR(IRR(C19:H19),"n/a") -> 0.53661366
B23: IRR is the annualized return on the cash left in the deal (Year 0), including annual cash flow and net proceeds from a sale at the end of Year 5. Yellow cells are assumptions you can change. Debt service is held flat (30-yr fixed refinance); operating expenses grow at the rate above.
